consurfDB/__init__.py
consurfDB/residue_type.py
consurfDB/consurf/__init__.py
consurfDB/consurf/alt.py
consurfDB/consurf/base.py
consurfDB/consurf/extras.py
ConsurfDB_client_API-1.0.dist-info/LICENSE
ConsurfDB_client_API-1.0.dist-info/METADATA
ConsurfDB_client_API-1.0.dist-info/WHEEL
ConsurfDB_client_API-1.0.dist-info/top_level.txt
ConsurfDB_client_API-1.0.dist-info/RECORD
