Metadata-Version: 2.1
Name: ConsurfDB-client-API
Version: 1.0
Summary: Python3 client API for ConsurfDB
Home-page: https://github.com/matteoferla/ConsurfDB-client-API
Author: Matteo Ferla
Author-email: matteo.ferla@gmail.com
License: MIT
Platform: UNKNOWN
Classifier: Development Status :: 5 - Production/Stable
Classifier: Intended Audience :: Science/Research
Classifier: Topic :: Scientific/Engineering :: Bio-Informatics
Classifier: License :: OSI Approved :: MIT License
Classifier: Programming Language :: Python :: 3.7
Classifier: Programming Language :: Python :: 3.8
Classifier: Programming Language :: Python :: 3.9
Classifier: Operating System :: OS Independent
License-File: LICENSE
Requires-Dist: typing-extensions
